med_discover_ai/__init__.py
med_discover_ai/chunking.py
med_discover_ai/config.py
med_discover_ai/embeddings.py
med_discover_ai/evaluation.py
med_discover_ai/gradio_app.py
med_discover_ai/gradio_app1.py
med_discover_ai/index.py
med_discover_ai/llm_inference.py
med_discover_ai/main.py
med_discover_ai/pdf_utils.py
med_discover_ai/retrieval.py
med_discover_ai/statistical_analysis.py
med_discover_ai-1.0.6.dist-info/METADATA
med_discover_ai-1.0.6.dist-info/WHEEL
med_discover_ai-1.0.6.dist-info/entry_points.txt
med_discover_ai-1.0.6.dist-info/RECORD
